CommonLibrary/Custom_Controls.py
CommonLibrary/Data_Comparision.py
CommonLibrary/DecryptUtils.py
CommonLibrary/EncryptUtil.py
CommonLibrary/WarningRemover.py
CommonLibrary/__init__.py
CommonLibrary/logging_config.py
bpx_CommonLibrary-0.1.0.dist-info/METADATA
bpx_CommonLibrary-0.1.0.dist-info/WHEEL
bpx_CommonLibrary-0.1.0.dist-info/top_level.txt
bpx_CommonLibrary-0.1.0.dist-info/RECORD
