Metadata-Version: 2.1
Name: bpx-CommonLibrary
Version: 0.1.0
Summary: A library for Common Keywords.
Home-page: https://dev.azure.com/bpx/Data%20Science%20and%20Digital%20Solutions/_git/RPA-Common-Library
Author: Gowrishankar Venkatesan
Author-email: Gowrishankar.Venkatesan@Ltimindtree.com
Classifier: Programming Language :: Python :: 3
Classifier: Programming Language :: Python :: 3.8
Classifier: Programming Language :: Python :: 3.9
Classifier: Programming Language :: Python :: 3.10
Classifier: Programming Language :: Python :: 3.11
Classifier: License :: OSI Approved :: Apache Software License
Classifier: Operating System :: OS Independent
Classifier: Topic :: Software Development :: Testing
Classifier: Topic :: Software Development :: Testing :: Acceptance
Classifier: Framework :: Robot Framework
Requires-Python: >=3.8.0
Requires-Dist: robotframework<8.0,>=4.0.2
Requires-Dist: docutils
Requires-Dist: Pygments
Provides-Extra: xls
Requires-Dist: pandas; extra == "xls"
Requires-Dist: xlrd>=1.2.0; extra == "xls"
Requires-Dist: openpyxl; extra == "xls"
